docxfill/__init__.py
docxfill/fill.py
docxfill-1.0.7.dist-info/licenses/LICENSE
docxfill-1.0.7.dist-info/METADATA
docxfill-1.0.7.dist-info/WHEEL
docxfill-1.0.7.dist-info/top_level.txt
docxfill-1.0.7.dist-info/RECORD
